fightchurn/__init__.py
fightchurn/run_churn_listing.py
fightchurn/churnsim/__init__.py
fightchurn/churnsim/behavior.py
fightchurn/churnsim/churndb.py
fightchurn/churnsim/churnsim.py
fightchurn/churnsim/customer.py
fightchurn/churnsim/utility.py
fightchurn/churnsim/conf/__init__.py
fightchurn/churnsim/conf/biznet5_addons.csv
fightchurn/churnsim/conf/biznet5_app.csv
fightchurn/churnsim/conf/biznet5_country.csv
fightchurn/churnsim/conf/biznet5_plans.csv
fightchurn/churnsim/conf/biznet5_population.csv
fightchurn/churnsim/conf/biznet5_updownchurn.csv
fightchurn/churnsim/conf/biznet5_utility.csv
fightchurn/churnsim/conf/crm5.yaml
fightchurn/churnsim/conf/crm5_addons.csv
fightchurn/churnsim/conf/crm5_appstore1.csv
fightchurn/churnsim/conf/crm5_appstore2.csv
fightchurn/churnsim/conf/crm5_country.csv
fightchurn/churnsim/conf/crm5_plans.csv
fightchurn/churnsim/conf/crm5_web.csv
fightchurn/churnsim/conf/crm6.yaml
fightchurn/churnsim/conf/crm6_addons.csv
fightchurn/churnsim/conf/crm6_appstore1.csv
fightchurn/churnsim/conf/crm6_appstore2.csv
fightchurn/churnsim/conf/crm6_country.csv
fightchurn/churnsim/conf/crm6_plans.csv
fightchurn/churnsim/conf/crm6_web.csv
fightchurn/churnsim/conf/default.yaml
fightchurn/churnsim/conf/negcor_behavior.csv
fightchurn/churnsim/conf/negcor_behavior_cov.csv
fightchurn/churnsim/conf/negcor_utility.csv
fightchurn/churnsim/conf/socialnet7.yaml
fightchurn/churnsim/conf/socialnet7_appstore1.csv
fightchurn/churnsim/conf/socialnet7_appstore2.csv
fightchurn/churnsim/conf/socialnet7_plans.csv
fightchurn/churnsim/conf/socialnet7_web.csv
fightchurn/churnsim/conf/test.yaml
fightchurn/churnsim/conf/test_plans.csv
fightchurn/churnsim/conf/test_web.csv
fightchurn/churnsim/schema/__init__.py
fightchurn/churnsim/schema/churn_by_plan.sql
fightchurn/churnsim/schema/create_account.sql
fightchurn/churnsim/schema/create_active_period.sql
fightchurn/churnsim/schema/create_active_week.sql
fightchurn/churnsim/schema/create_event.sql
fightchurn-1.1.6.dist-info/LICENSE.md
fightchurn-1.1.6.dist-info/METADATA
fightchurn-1.1.6.dist-info/WHEEL
fightchurn-1.1.6.dist-info/top_level.txt
fightchurn-1.1.6.dist-info/RECORD
