Metadata-Version: 2.1
Name: fightchurn
Version: 1.1.6
Summary: Code from the book Fighting Churn With Data
Home-page: https://github.com/carl24k/fight-churn
Author: Carl Gold
Author-email: carl@fightchurnwithdata.com
Project-URL: Bug Tracker, https://github.com/carl24k/fight-churn/issues
Classifier: Programming Language :: Python :: 3
Classifier: License :: OSI Approved :: MIT License
Classifier: Operating System :: OS Independent
Requires-Python: >=3.9,<3.10
License-File: LICENSE.md
Requires-Dist: antlr4-python3-runtime ==4.9.3.0
Requires-Dist: bleach ==6.0.0
Requires-Dist: build ==0.10.0
Requires-Dist: certifi ==2023.7.22
Requires-Dist: chardet ==5.2.0
Requires-Dist: cloudpickle ==2.2.1
Requires-Dist: colorama ==0.4.6
Requires-Dist: cycler ==0.11.0
Requires-Dist: docutils ==0.20.1
Requires-Dist: greenlet ==2.0.2
Requires-Dist: hydra-core ==1.3.2
Requires-Dist: importlib-metadata ==6.8.0
Requires-Dist: joblib ==1.3.2
Requires-Dist: keyring ==24.2.0
Requires-Dist: kiwisolver ==1.4.4
Requires-Dist: llvmlite ==0.40.1
Requires-Dist: matplotlib ==3.7.2
Requires-Dist: numba ==0.57.1
Requires-Dist: numpy ==1.24.4
Requires-Dist: packaging ==23.1
Requires-Dist: pandas ==1.5.3
Requires-Dist: patsy ==0.5.3
Requires-Dist: Pillow ==10.0.1
Requires-Dist: filelock ==3.12.2
Requires-Dist: omegaconf ==2.3.0
Requires-Dist: pkginfo ==1.9.6
Requires-Dist: postgres ==4.0
Requires-Dist: psycopg2-binary ==2.9.7
Requires-Dist: psycopg2-pool ==1.1
Requires-Dist: Pygments ==2.16.1
Requires-Dist: pyparsing ==2.4.7
Requires-Dist: python-dateutil ==2.8.2
Requires-Dist: pytz ==2023.3
Requires-Dist: pytest
Requires-Dist: readme-renderer ==41.0
Requires-Dist: requests ==2.31.0
Requires-Dist: requests-toolbelt ==1.0.0
Requires-Dist: rfc3986 ==1.5.0
Requires-Dist: scikit-learn ==1.3.0
Requires-Dist: scipy ==1.11.2
Requires-Dist: shap ==0.42.1
Requires-Dist: six ==1.16.0
Requires-Dist: slicer ==0.0.7
Requires-Dist: SQLAlchemy ==1.4.9
Requires-Dist: statsmodels ==0.14.0
Requires-Dist: toml ==0.10.2
Requires-Dist: tqdm ==4.66.1
Requires-Dist: twine ==4.0.2
Requires-Dist: urllib3 ==2.0.7
Requires-Dist: webencodings ==0.5.1
Requires-Dist: xgboost ==1.7.6
Requires-Dist: zipp ==3.16.2
